pixv/.gitignore
pixv/__init__.py
pixv/feature.py
pixv/file_server.py
pixv/.cph/.A_Brick_Wall.cpp_3c6971ce75a4fb8280654d41645a6957.prob
pixv/.cph/.A_We_Got_Everything_Covered.cpp_360214c29e797ad454367a0fb8ff0e17.prob
pixv/.cph/.B_A_Balanced_Problemset.cpp_b760b9d406559f853027563b8285ed41.prob
pixv/.cph/.B_Minimize_Inversions.cpp_384ac98d3bc7d3bc954b4bea7a6f0646.prob
pixv/.cph/.C_Did_We_Get_Everything_Covered.cpp_f08b1383b2d4cdd2633f8d71f10d8d75.prob
pixv/.cph/.C_XOR_distance.cpp_10da071f92c3b64e7a3b1adefb342b3c.prob
pixv/.vscode/settings.json
pixv/Node/__init__.py
pixv/Node/diffs.py
pixv/Node/nodes.py
pixv/server/__init__.py
pixv/server/pull_file.py
pixv/server/push_file.py
pixv/utils/Pixels.py
pixv/utils/__init__.py
pixv/utils/hash.py
pixv/utils/helper.py
pixv-0.2.1.dist-info/METADATA
pixv-0.2.1.dist-info/WHEEL
pixv-0.2.1.dist-info/entry_points.txt
pixv-0.2.1.dist-info/licenses/LICENSE
pixv-0.2.1.dist-info/RECORD
