Metadata-Version: 2.1
Name: pixv
Version: 0.2.1
Summary: multiple outgoing nodes bug fixed
Project-URL: Homepage, https://github.com/ReallyJaegar/PixV
Author-email: Som Shekhar Sharma <sharmathat@gmail.com>, Dhruv Sagar <dhruvsagar24nd@gmail.com>
License: MIT License
License-File: LICENSE
Classifier: License :: OSI Approved :: MIT License
Classifier: Operating System :: OS Independent
Classifier: Programming Language :: Python :: 3
Requires-Python: >=3.10.0
Requires-Dist: click>=8.1.7
Requires-Dist: matplotlib>=3.8.2
Requires-Dist: numpy>=1.26.1
Requires-Dist: pillow>=10.0.1
Requires-Dist: requests>=2.31.0
